everstone/__init__.py
everstone/bases.py
everstone/database.py
everstone/exceptions.py
everstone/sql/__init__.py
everstone/sql/aggregates.py
everstone/sql/column.py
everstone/sql/comparisons.py
everstone/sql/constraints.py
everstone/sql/schema.py
everstone/sql/table.py
everstone/sql/types.py
everstone-0.1.2.dist-info/LICENSE
everstone-0.1.2.dist-info/WHEEL
everstone-0.1.2.dist-info/METADATA
everstone-0.1.2.dist-info/RECORD
